bhr_client/__init__.py
bhr_client/block_manager.py
bhr_client/cli.py
bhr_client/rest.py
bhr_client/run.py
bhr_client/source_blocker.py
bhr_client-1.6.dist-info/LICENSE.txt
bhr_client-1.6.dist-info/METADATA
bhr_client-1.6.dist-info/WHEEL
bhr_client-1.6.dist-info/entry_points.txt
bhr_client-1.6.dist-info/top_level.txt
bhr_client-1.6.dist-info/RECORD
