Metadata-Version: 2.1
Name: bhr-client
Version: 1.6
Summary: BHR Client
Home-page: https://github.com/ncsa/bhr-client
Author: Justin Azoff
Author-email: JAzoff@illinois.edu
License: MIT
Keywords: bhr
Platform: UNKNOWN
Requires-Dist: requests (>=2.0)
Requires-Dist: arrow (==0.10.0)
Provides-Extra: cli
Requires-Dist: Click ; extra == 'cli'
